pyimgtool/__init__.py
pyimgtool/__main__.py
pyimgtool/args.py
pyimgtool/data_structures.py
pyimgtool/exceptions.py
pyimgtool/image.py
pyimgtool/resize.py
pyimgtool/utils.py
pyimgtool/version.py
pyimgtool/watermark.py
pyimgtool/fonts/SourceSansPro-Regular.ttf
pyimgtool-0.0.1a8.dist-info/LICENSE
pyimgtool-0.0.1a8.dist-info/METADATA
pyimgtool-0.0.1a8.dist-info/WHEEL
pyimgtool-0.0.1a8.dist-info/entry_points.txt
pyimgtool-0.0.1a8.dist-info/top_level.txt
pyimgtool-0.0.1a8.dist-info/RECORD
