Metadata-Version: 2.1
Name: pyimgtool
Version: 0.0.1a8
Summary: Tool to help prep images for web sharing
Home-page: https://github.com/comfortablynick/pyimgtool
Author: Nick Murphy
Author-email: comfortablynick@gmail.com
License: UNKNOWN
Project-URL: Bug Reports, https://github.com/comfortablynick/pyimgtool/issues
Project-URL: Source, https://github.com/comfortablynick/pyimgtool
Platform: UNKNOWN
Classifier: Development Status :: 2 - Pre-Alpha
Classifier: Programming Language :: Python :: 3 :: Only
Classifier: License :: OSI Approved :: MIT License
Requires-Python: >=3.6
Requires-Dist: pillow
Requires-Dist: piexif
Requires-Dist: attrs
Requires-Dist: sty
Requires-Dist: opencv-python
Requires-Dist: numpy
Requires-Dist: plotille
